{
  "parent": "nomadicrealms:nomadic/hoarders_delight",
  "display": {
    "icon": {
      "id": "minecraft:iron_ingot"
    },
    "title": "Iron Looter",
    "description": "A new tool is in your future, use it wisely.",
    "announce_to_chat": false,
    "show_toast": true
  },
  "criteria": {
    "looted_iron": {
      "trigger": "minecraft:inventory_changed",
      "conditions": {
        "items": [
          {
            "items": [
              "minecraft:iron_nugget",
              "minecraft:iron_ingot"
            ]
          }
        ]
      }
    }
  }
}